clickhouse_orm/__init__.py
clickhouse_orm/database.py
clickhouse_orm/engines.py
clickhouse_orm/fields.py
clickhouse_orm/funcs.py
clickhouse_orm/migrations.py
clickhouse_orm/models.py
clickhouse_orm/query.py
clickhouse_orm/session.py
clickhouse_orm/system_models.py
clickhouse_orm/utils.py
clickhouse_orm/aio/__init__.py
clickhouse_orm/aio/database.py
clickhouse_orm/contrib/__init__.py
clickhouse_orm/contrib/geo/__init__.py
clickhouse_orm/contrib/geo/fields.py
ch_orm-0.2.3.dist-info/LICENSE
ch_orm-0.2.3.dist-info/METADATA
ch_orm-0.2.3.dist-info/WHEEL
ch_orm-0.2.3.dist-info/top_level.txt
ch_orm-0.2.3.dist-info/RECORD
