Metadata-Version: 2.1
Name: ch-orm
Version: 0.2.3
Summary: A Python library for working with the ClickHouse database
License: BSD License
Project-URL: Homepage, https://github.com/sswest/ch-orm
Project-URL: Documentation, https://sswest.github.io/ch-orm/
Keywords: ClickHouse,ORM,DB,DATABASE,OLAP
Classifier: Programming Language :: Python :: 3.7
Classifier: Programming Language :: Python :: 3.8
Classifier: Programming Language :: Python :: 3.9
Classifier: Programming Language :: Python :: 3.10
Classifier: Operating System :: OS Independent
Classifier: Topic :: Software Development :: Libraries :: Python Modules
Classifier: Topic :: Database
License-File: LICENSE
Requires-Dist: httpx (>=0.18.0)
Requires-Dist: pytz
Requires-Dist: iso8601 (>=0.1.12)
Requires-Dist: setuptools
